pdm_dotenv/__init__.py
pdm_dotenv-0.3.0.dist-info/METADATA
pdm_dotenv-0.3.0.dist-info/WHEEL
pdm_dotenv-0.3.0.dist-info/entry_points.txt
pdm_dotenv-0.3.0.dist-info/licenses/LICENSE
pdm_dotenv-0.3.0.dist-info/RECORD
