Metadata-Version: 2.1
Name: pdm-dotenv
Version: 0.3.0
Summary: A pdm plugin that automatically loads .env files
Project-URL: Repository, https://github.com/zdog234/pdm-dotenv
Project-URL: Homepage, https://github.com/zdog234/pdm-dotenv
Author-email: Zane Dufour <zane@znd4.me>
License: MIT
License-File: LICENSE
Classifier: Development Status :: 3 - Alpha
Classifier: Programming Language :: Python :: 3
Requires-Python: >=3.8
Requires-Dist: pdm>=2.5.2
Requires-Dist: python-dotenv>=1.0.0
